{
	"Version": 1,
	"WorldDescription":
	{
		"islandId": "EEF6D5A0D54944C9238233D180EC4FEF",
		"WorldName": "Shit Earth",
		"CreationTime": 6.3913033971152998e+17,
		"WorldPresetType": "Medium",
		"WorldSettings":
		{
			"BoolParameters":
			{
				"{\"TagName\": \"WDS.Parameter.Coop.SharedQuests\"}": true,
				"{\"TagName\": \"WDS.Parameter.EasyExplore\"}": false
			},
			"FloatParameters":
			{
				"{\"TagName\": \"WDS.Parameter.MobHealthMultiplier\"}": 1,
				"{\"TagName\": \"WDS.Parameter.MobDamageMultiplier\"}": 1,
				"{\"TagName\": \"WDS.Parameter.ShipsHealthMultiplier\"}": 1,
				"{\"TagName\": \"WDS.Parameter.ShipsDamageMultiplier\"}": 1,
				"{\"TagName\": \"WDS.Parameter.BoardingDifficultyMultiplier\"}": 1,
				"{\"TagName\": \"WDS.Parameter.Coop.StatsCorrectionModifier\"}": 1,
				"{\"TagName\": \"WDS.Parameter.Coop.ShipStatsCorrectionModifier\"}": 0
			},
			"TagParameters":
			{
				"{\"TagName\": \"WDS.Parameter.CombatDifficulty\"}":
				{
					"TagName": "WDS.Parameter.CombatDifficulty.Normal"
				}
			}
		}
	}
}